koodous/__init__.py
koodous/cli.py
koodous/koodous.py
koodous/utils.py
koodous_py_iantruslove-0.9.dist-info/LICENSE.txt
koodous_py_iantruslove-0.9.dist-info/METADATA
koodous_py_iantruslove-0.9.dist-info/WHEEL
koodous_py_iantruslove-0.9.dist-info/entry_points.txt
koodous_py_iantruslove-0.9.dist-info/top_level.txt
koodous_py_iantruslove-0.9.dist-info/RECORD
