Metadata-Version: 2.1
Name: koodous-py-iantruslove
Version: 0.9
Summary: Module to interact with Koodous API
Home-page: https://koodous.com/
Author: Ian Truslove
Author-email: ian.truslove@gmail.com
License: Apache Version 2
Keywords: koodous,api,sdk,python,android,apk,malware
Platform: UNKNOWN
Requires-Dist: click
Requires-Dist: coloredlogs
Requires-Dist: humanfriendly
Requires-Dist: Pygments
Requires-Dist: requests
Requires-Dist: androguard
Requires-Dist: certifi
